restiro/__init__.py
restiro/constants.py
restiro/documentor.py
restiro/exceptions.py
restiro/helpers.py
restiro/mock_server.py
restiro/cli/__init__.py
restiro/generators/__init__.py
restiro/generators/base.py
restiro/generators/json.py
restiro/generators/markdown.py
restiro/generators/mock.py
restiro/middlewares/__init__.py
restiro/middlewares/webtest.py
restiro/models/__init__.py
restiro/models/document.py
restiro/models/example.py
restiro/models/parameters.py
restiro/models/resource.py
restiro/models/root.py
restiro/models/translation_mixin.py
restiro/parser/__init__.py
restiro/parser/definition.py
restiro/parser/docstring.py
restiro/parser/resource.py
restiro-0.17.0.dist-info/LICENSE
restiro-0.17.0.dist-info/METADATA
restiro-0.17.0.dist-info/WHEEL
restiro-0.17.0.dist-info/entry_points.txt
restiro-0.17.0.dist-info/top_level.txt
restiro-0.17.0.dist-info/RECORD
