Metadata-Version: 2.1
Name: restiro
Version: 0.17.0
Summary: RESTful API documentation generator
Home-page: http://github.com/meyt/restiro
Author: Mahdi Ghane.g
License: GPLv3
Keywords: api_documentation api document_generator
Platform: UNKNOWN
Classifier: Development Status :: 1 - Planning
Classifier: Environment :: Console
Classifier: Intended Audience :: Developers
Classifier: License :: OSI Approved :: MIT License
Classifier: Operating System :: POSIX :: Linux
Classifier: Operating System :: Unix
Classifier: Programming Language :: Python :: 3 :: Only
Classifier: Topic :: Software Development :: Documentation
Classifier: Topic :: Documentation
Classifier: Topic :: Software Development :: Build Tools
